setup.py
src/DBScan.cpp
src/DBScan.h
src/RTree.h
src/c_test_prog.cpp
src/c_test_prog.h
src/globals.h
src/main.cpp
src/prototypes.h
src/schedule.cpp
src/schedule.h
src/structs.h
src/tree_functions.cpp
vdbscan/__init__.py
vdbscan/variantdbscan.py
vdbscan.egg-info/PKG-INFO
vdbscan.egg-info/SOURCES.txt
vdbscan.egg-info/dependency_links.txt
vdbscan.egg-info/not-zip-safe
vdbscan.egg-info/requires.txt
vdbscan.egg-info/top_level.txt
vdbscan/examples/test_dataset.csv
vdbscan/examples/variant_example.py
vdbscan/examples/vtest.py