Metadata-Version: 1.1
Name: vdbscan
Version: 0.9.2
Summary: Variant DBSCAN
Home-page: https://github.com/MITHaystack/VariantDBSCAN
Author: MITHAGI
Author-email: UNKNOWN
License: UNKNOWN
Platform: UNKNOWN
Classifier: Topic :: Scientific/Engineering
Classifier: Intended Audience :: Science/Research
Classifier: License :: OSI Approved :: MIT License
Classifier: Programming Language :: Python :: 2
Classifier: Programming Language :: Python :: 3
Classifier: Programming Language :: C++
Classifier: Operating System :: POSIX :: Linux
